C-UnidadeLogicaAritmetica/src/FullAdder.vhd
-- Elementos de Sistemas
-- by Luciano Soares
-- FullAdder.vhd

-- Implementa Full Adder

Library ieee;
use ieee.std_logic_1164.all;

entity FullAdder is
	port(
		a,b,c:      in STD_LOGIC;   -- entradas
		soma,vaium: out STD_LOGIC   -- sum e carry
	);
end entity;

architecture rtl of FullAdder is
  -- Aqui declaramos sinais (fios auxiliares)
  -- e componentes (outros módulos) que serao
  -- utilizados nesse modulo.

begin
  soma <= a xor b xor c;
  vaium <= (a and b) or (c and a) or (c and b);

end architecture;

C-UnidadeLogicaAritmetica/teste_cocotb/waves/fulladder.vcd
$date
  Fri Sep 23 22:50:06 2022
$end
$version
  GHDL v0
$end
$timescale
  1 fs
$end
$scope module standard $end
$upscope $end
$scope module std_logic_1164 $end
$upscope $end
$scope module fulladder $end
$var reg 1 ! a $end
$var reg 1 " b $end
$var reg 1 # c $end
$var reg 1 $ soma $end
$var reg 1 % vaium $end
$upscope $end
$enddefinitions $end
#0
0!
0"
0#
0$
0%
#1000000
#2000000
1"
1$
#3000000
#4000000
1!
0"
#5000000
#6000000
1"
0$
1%
#7000000
#8000000
0!
0"
1#
1$
0%
#9000000
#10000000
1"
0$
1%
#11000000
#12000000
1!
0"
#13000000
#14000000
1"
1$
